setup.py
src/pytomd/__init__.py
src/pytomd/__main__.py
src/pytomd.egg-info/PKG-INFO
src/pytomd.egg-info/SOURCES.txt
src/pytomd.egg-info/dependency_links.txt
src/pytomd.egg-info/entry_points.txt
src/pytomd.egg-info/not-zip-safe
src/pytomd.egg-info/top_level.txt
src/pytomd/modules/__init__.py
src/pytomd/modules/data.py
src/pytomd/modules/manager.py
src/pytomd/modules/scanner.py
src/pytomd/modules/transform.py