Metadata-Version: 1.1
Name: pytomd
Version: 1.0.1
Summary: Easy python project document generator to github README.md file
Home-page: https://github.com/itow0001/pytomd
Author: Ian Itow
Author-email: itow0001@gmail.com
License: MIT
Platform: UNKNOWN
Classifier: Topic :: Software Development :: Build Tools
Classifier: Programming Language :: Python :: 2.7
